hackedu_cli-0.1.8.data/scripts/hackedu
integrations/__init__.py
integrations/sonarqube.py
hackedu_cli-0.1.8.dist-info/METADATA
hackedu_cli-0.1.8.dist-info/WHEEL
hackedu_cli-0.1.8.dist-info/top_level.txt
hackedu_cli-0.1.8.dist-info/RECORD
